rdns_reaper/__init__.py
rdns_reaper/rdns_reaper.py
rdns_reaper-0.1.2.dist-info/METADATA
rdns_reaper-0.1.2.dist-info/WHEEL
rdns_reaper-0.1.2.dist-info/licenses/LICENSE
rdns_reaper-0.1.2.dist-info/RECORD
