Metadata-Version: 2.3
Name: rdns_reaper
Version: 0.1.2
Summary: Reverse DNS lookup engine
Project-URL: Home Page, https://github.com/mullaneywt/rdns_reaper
Project-URL: Bug Tracker, https://github.com/mullaneywt/rdns_reaper/issues
Project-URL: Source, https://github.com/mullaneywt/rdns_reaper
Project-URL: Documentation, https://rdns-reaper.readthedocs.io
Author-email: Will Mullaney <rdns-reaper@mullaneywt.anonaddy.com>
License: GNU GPL v3.0
License-File: LICENSE
Keywords: dns,reverse
Classifier: Intended Audience :: Developers
Classifier: Intended Audience :: Information Technology
Classifier: Intended Audience :: System Administrators
Classifier: Intended Audience :: Telecommunications Industry
Classifier: Natural Language :: English
Classifier: Operating System :: OS Independent
Classifier: Programming Language :: Python :: 3
Classifier: Programming Language :: Python :: 3.7
Classifier: Programming Language :: Python :: 3.8
Classifier: Programming Language :: Python :: 3.9
Classifier: Programming Language :: Python :: 3.10
Classifier: Programming Language :: Python :: 3.11
Classifier: Programming Language :: Python :: 3.12
Classifier: Topic :: Internet
Classifier: Topic :: Internet :: Name Service (DNS)
Classifier: Topic :: Software Development
Classifier: Topic :: Software Development :: Libraries
Classifier: Topic :: Software Development :: Libraries :: Python Modules
Classifier: Topic :: Software Development :: Quality Assurance
Classifier: Topic :: Software Development :: Testing
Classifier: Topic :: System :: Networking
Classifier: Topic :: Utilities
Requires-Python: >=3.7
Requires-Dist: netaddr>=0.8.0
Requires-Dist: ruamel-yaml>=0.18.6
